moodlmth/__init__.py
moodlmth/cli.py
moodlmth/const.py
moodlmth/converter.py
moodlmth/protocols.py
moodlmth/py_converter.py
moodlmth/yaml_converter.py
moodlmth-0.4.0.dist-info/METADATA
moodlmth-0.4.0.dist-info/WHEEL
moodlmth-0.4.0.dist-info/entry_points.txt
moodlmth-0.4.0.dist-info/top_level.txt
moodlmth-0.4.0.dist-info/RECORD
