Metadata-Version: 2.1
Name: moodlmth
Version: 0.4.0
Summary: Convert raw HTML pages into python source code
Home-page: https://github.com/sayanarijit/moodlmth
Author: Arijit Basu
Author-email: sayanarijit@gmail.com
License: MIT
Keywords: html dom builder
Platform: Any
Classifier: Development Status :: 3 - Alpha
Classifier: Intended Audience :: Developers
Classifier: Intended Audience :: Information Technology
Classifier: Intended Audience :: Other Audience
Classifier: License :: OSI Approved :: MIT License
Classifier: Natural Language :: English
Classifier: Programming Language :: Python :: 3.6
Classifier: Programming Language :: Python :: 3.7
Classifier: Topic :: Utilities
Classifier: Topic :: Software Development
Classifier: Operating System :: MacOS
Classifier: Operating System :: Unix
Classifier: Operating System :: POSIX
Classifier: Operating System :: Microsoft
Requires-Dist: black (==19.3b0)
Requires-Dist: htmldoom (>=0.9.0<0.10.0)
Requires-Dist: htmlmin (==0.1.12)
Requires-Dist: requests (==2.22.0)
Requires-Dist: typing-extensions (==3.7.4)
Provides-Extra: dev
Requires-Dist: pytest (==4.4.1) ; extra == 'dev'
Requires-Dist: pytest-cov (==2.7.1) ; extra == 'dev'
Requires-Dist: mypy (==0.710) ; extra == 'dev'
Requires-Dist: lxml (==4.3.4) ; extra == 'dev'
Requires-Dist: typecov (==0.2.1) ; extra == 'dev'
Requires-Dist: tox (==3.12.1) ; extra == 'dev'
Provides-Extra: testing
Requires-Dist: pytest (==4.4.1) ; extra == 'testing'
Requires-Dist: pytest-cov (==2.7.1) ; extra == 'testing'
Requires-Dist: mypy (==0.710) ; extra == 'testing'
Requires-Dist: lxml (==4.3.4) ; extra == 'testing'
Requires-Dist: typecov (==0.2.1) ; extra == 'testing'
